kbckit/__init__.py
kbckit/dataset.py
kbckit-0.1.0.dist-info/WHEEL
kbckit-0.1.0.dist-info/METADATA
kbckit-0.1.0.dist-info/RECORD
