Metadata-Version: 2.1
Name: kbckit
Version: 0.1.0
Summary: Toolkit for KBC
Home-page: UNKNOWN
License: UNKNOWN
Author: Ryo Takahashi
Author-email: reiyw.setuve@gmail.com
Requires-Python: >=3.6,<4.0
Classifier: Programming Language :: Python :: 3
Classifier: Programming Language :: Python :: 3.6
Classifier: Programming Language :: Python :: 3.7
Requires-Dist: click (>=7.0,<8.0)
Requires-Dist: logzero (>=1.5,<2.0)
Requires-Dist: pandas (>=0.23.4,<0.24.0)
Requires-Dist: requests (>=2.20,<3.0)
